.gitignore
LICENSE.md
README.md
setup.py
docs/.gitignore
docs/render.go
docs/render.py
docs/images/bend.png
docs/images/bend_linear.png
docs/images/bend_radial.png
docs/images/blend.png
docs/images/blobby.jpg
docs/images/blobby.png
docs/images/box.png
docs/images/box2.png
docs/images/butterfly.png
docs/images/capped_cone.png
docs/images/capped_cylinder.png
docs/images/capsule.png
docs/images/circular_array.png
docs/images/customizable_box.png
docs/images/customizable_lid.png
docs/images/cylinder.png
docs/images/difference.png
docs/images/dilate.png
docs/images/dodecahedron.png
docs/images/ellipsoid.png
docs/images/elongate.png
docs/images/erode.png
docs/images/example.jpg
docs/images/example.png
docs/images/extrude.png
docs/images/extrude_to.png
docs/images/gearlike.jpg
docs/images/gearlike.png
docs/images/icosahedron.png
docs/images/intersection.png
docs/images/knurling.jpg
docs/images/knurling.png
docs/images/meshview.png
docs/images/octahedron.png
docs/images/orient.png
docs/images/plane.png
docs/images/pyramid.png
docs/images/repeat.png
docs/images/revolve.png
docs/images/rotate.png
docs/images/rounded_box.png
docs/images/rounded_cone.png
docs/images/rounded_cylinder.png
docs/images/scale.png
docs/images/shell.png
docs/images/show_slice.png
docs/images/slab.png
docs/images/slice.png
docs/images/smooth_difference.png
docs/images/smooth_intersection.png
docs/images/smooth_union.png
docs/images/sphere.png
docs/images/tetrahedron.png
docs/images/text-large.png
docs/images/text.png
docs/images/torus.png
docs/images/transition_linear.png
docs/images/transition_radial.png
docs/images/translate.png
docs/images/twist.png
docs/images/union.png
docs/images/weave.jpg
docs/images/weave.png
docs/images/wireframe_box.png
docs/images/wrap_around.png
examples/blobby.py
examples/butterfly.png
examples/customizable_box.py
examples/example.py
examples/gearlike.py
examples/image.py
examples/knurling.py
examples/pawn.py
examples/text.py
examples/weave.py
sdf/__init__.py
sdf/d2.py
sdf_fork.egg-info/PKG-INFO
sdf_fork.egg-info/SOURCES.txt
sdf_fork.egg-info/dependency_links.txt
sdf_fork.egg-info/requires.txt
sdf_fork.egg-info/top_level.txt