Metadata-Version: 2.1
Name: sdf-fork
Version: 0.1.1
Summary: Generate 3D meshes from signed distance functions.
Home-page: UNKNOWN
Author: Michael Fogleman
Author-email: michael.fogleman@gmail.com
License: MIT
Platform: UNKNOWN
Classifier: Development Status :: 3 - Alpha
Classifier: Intended Audience :: Developers
Classifier: Natural Language :: English
Classifier: License :: OSI Approved :: MIT License
Classifier: Programming Language :: Python
Classifier: Programming Language :: Python :: 3
License-File: LICENSE.md
